{"id":"capitec-bank","name":"Capitec Bank","categorySlug":"banking","categoryName":"Banking","categoryIcon":"fa-building-columns","logo":"https://upload.wikimedia.org/wikipedia/en/thumb/9/9a/Capitec_Bank_logo.svg/1200px-Capitec_Bank_logo.svg.png","website":"https://www.capitecbank.co.za","overallScore":76,"verdict":"GO WITH CAUTION","categoryScores":{"Compliance":{"score":18.0,"max":20.0,"description":"SARB PA licensed; no 2025/26 major regulatory action; FSCA FSP; POPIA compliant."},"Customer Satisfaction":{"score":20.0,"max":25.0,"description":"HelloPeter 3.3/5; app Store 4.7/5 with 400K iOS; strong net satisfaction overall."},"Product Value":{"score":28.0,"max":35.0,"description":"Competitive rates, inclusive low-fee structure, but some fee increases noted 2026."},"Innovation":{"score":8.0,"max":10.0,"description":"Capitec Connect MVNO, PayShap, Apple Pay, digital-first. Strong fintech moves."},"Customer Support":{"score":7.0,"max":15.0,"description":"24/7 call centre; branches; complaints of fraud resolution delays, card blocks."},"Accessibility & Security":{"score":6.0,"max":10.0,"description":"Major app (4.5/5 GP), branches nationwide, but recent data breach/hack incidents and fraud complaints."}},"scoringCategories":[{"name":"Compliance","max":20},{"name":"Customer Satisfaction","max":25},{"name":"Product Value","max":35},{"name":"Innovation","max":10},{"name":"Customer Support","max":15},{"name":"Accessibility & Security","max":10}],"keyFeatures":["Global One account","Capitec Connect SIM","multi-currency","Apple Pay","PayShap","1% cashback"],"pricing":[{"name":"Pricing","cost":"Pricing: R7/mo fee; ATM R9, card replace R130; Connect SIM from R29","features":""}],"appRatings":{"googlePlay":"4.5/5","ios":"4.7/5","googlePlayScore":4.5,"iosScore":4.7},"strengths":["large customer base","app quality","innovation","low fees","extensive ATM network"],"concerns":["fraud incidents","support delays","fee increases"],"socialSentiment":{"summary":"Mix: app praised, fraud complaints increase. Strong brand loyalty.","positive_themes":["easy banking","great app","cashback"],"common_concerns":["fraud","account frozen","slow support"]},"lastUpdated":"2026-03-05"}