{"id":"tempest-car-hire","name":"Tempest Car Hire","categorySlug":"car-rentals","categoryName":"Car Rentals","categoryIcon":"fa-key","logo":"https://tempestcarhire.co.za/wp-content/uploads/2022/04/Tempest-Logo.png","website":"https://www.tempestcarhire.co.za","overallScore":86,"verdict":"GO","categoryScores":{"Compliance":{"score":18.0,"max":20.0,"description":"Licensed SA car hire company, CPA compliant, no major violations found in 2025/2026 searches."},"Customer Satisfaction":{"score":22.0,"max":25.0,"description":"HelloPeter 4.74/5 (strong positive ratings); Google 4.4/5; praised for professionalism and fleet quality."},"Product Value":{"score":30.0,"max":35.0,"description":"Competitive rates; loyalty rewards; business rates; wide fleet including EVs; good value vs major brands."},"Innovation":{"score":8.0,"max":10.0,"description":"App booking, 360-degree vehicle inspection, EVs in fleet, loyalty program, modern booking system."},"Customer Support":{"score":13.0,"max":15.0,"description":"Responsive per reviews; professional at pickup/return; national network support."},"Accessibility & Security":{"score":8.0,"max":10.0,"description":"App booking; national presence; standard CPA/privacy compliance."}},"scoringCategories":[{"name":"Compliance","max":20},{"name":"Customer Satisfaction","max":25},{"name":"Product Value","max":35},{"name":"Innovation","max":10},{"name":"Customer Support","max":15},{"name":"Accessibility & Security","max":10}],"keyFeatures":["wide fleet including EVs","loyalty rewards","business rates","360-degree inspection","nationwide locations"],"pricing":[{"name":"Pricing","cost":"Pricing: From ~R300/day economy; competitive vs Avis/Hertz; business rates available","features":""}],"appRatings":{"googlePlay":"4.2/5","ios":"4.2/5","googlePlayScore":4.2,"iosScore":4.2},"strengths":["high HelloPeter/Google ratings","EV fleet innovation","competitive pricing","professional service"],"concerns":["smaller footprint vs Avis/Hertz","limited international presence"],"socialSentiment":{"summary":"Highly positive ratings; limited social data but reviews consistent.","positive_themes":["professional service","clean cars","easy booking","great rates"],"common_concerns":["limited locations vs big brands"]},"lastUpdated":"2026-03-05"}